sixfeetup.bowab-0.13-py3.8-nspkg.pth
sixfeetup/bowab/__init__.py
sixfeetup/bowab/api.py
sixfeetup/bowab/configuration.py
sixfeetup/bowab/subscribers.py
sixfeetup/bowab/db/__init__.py
sixfeetup/bowab/db/base.py
sixfeetup/bowab/db/types.py
sixfeetup/bowab/forms/__init__.py
sixfeetup/bowab/forms/widgets/__init__.py
sixfeetup/bowab/forms/widgets/colorpicker.py
sixfeetup/bowab/forms/widgets/csrf.py
sixfeetup/bowab/forms/widgets/recaptcha.py
sixfeetup/bowab/scripts/__init__.py
sixfeetup/bowab/scripts/initializedb.py
sixfeetup/bowab/tests/__init__.py
sixfeetup/bowab/tests/mocks.py
sixfeetup/bowab/tests/subscribers.py
sixfeetup.bowab-0.13.dist-info/METADATA
sixfeetup.bowab-0.13.dist-info/WHEEL
sixfeetup.bowab-0.13.dist-info/entry_points.txt
sixfeetup.bowab-0.13.dist-info/namespace_packages.txt
sixfeetup.bowab-0.13.dist-info/top_level.txt
sixfeetup.bowab-0.13.dist-info/RECORD
