Metadata-Version: 2.1
Name: sixfeetup.bowab
Version: 0.13
Summary: Helpful utilities for Pyramid projects
Home-page: https://github.com/sixfeetup/sixfeetup.bowab
Author: 
Author-email: 
License: gpl
Platform: UNKNOWN
Classifier: Programming Language :: Python
Requires-Dist: setuptools
Requires-Dist: pyramid
Requires-Dist: deform
Requires-Dist: colander
Requires-Dist: requests
Requires-Dist: SQLAlchemy
Requires-Dist: alembic
Requires-Dist: gaq-hub
Requires-Dist: zope.sqlalchemy (<=1.1)
Requires-Dist: psycopg2
Provides-Extra: test
Requires-Dist: coverage ; extra == 'test'
Requires-Dist: mock ; extra == 'test'
